webtransport/__init__.py
webtransport/__init__.pyi
webtransport/h2.pyi
webtransport/h3.pyi
webtransport/http2.pyi
webtransport/http3.pyi
webtransport/py.typed
webtransport/quic.pyi
webtransport/webtransport_ext.cpython-313-aarch64-linux-gnu.so
webtransport/webtransport_ext.pyi
webtransport/h2/__init__.py
webtransport/h2/client.py
webtransport/h2/server.py
webtransport/h3/__init__.py
webtransport/h3/client.py
webtransport/h3/server.py
webtransport/http2/__init__.py
webtransport/http2/client.py
webtransport/http2/server.py
webtransport/http3/__init__.py
webtransport/http3/client.py
webtransport/http3/server.py
webtransport/quic/__init__.py
webtransport/quic/client.py
webtransport/quic/server.py
webtransport_py-2026.1.0.dev0.dist-info/METADATA
webtransport_py-2026.1.0.dev0.dist-info/WHEEL
webtransport_py-2026.1.0.dev0.dist-info/RECORD
webtransport_py-2026.1.0.dev0.dist-info/licenses/LICENSE
